ibdcluster/analysis/__init__.py
ibdcluster/analysis/main.py
ibdcluster/callbacks/__init__.py
ibdcluster/callbacks/check_inputs.py
ibdcluster/cluster/__init__.py
ibdcluster/cluster/main.py
ibdcluster/cluster/phecode_percentages.py
ibdcluster/factory/__init__.py
ibdcluster/factory/factory.py
ibdcluster/factory/loader.py
ibdcluster/log/.gitignore
ibdcluster/log/__init__.py
ibdcluster/log/logger.py
ibdcluster/models/__init__.py
ibdcluster/models/cluster_class.py
ibdcluster/models/data_container.py
ibdcluster/models/indices.py
ibdcluster/models/networks.py
ibdcluster/models/pairs.py
ibdcluster/plugins/__init__.py
ibdcluster/plugins/allpair_writer.py
ibdcluster/plugins/network_writer.py
ibdcluster/plugins/phecode_pvalue_distributions.py
ibdcluster/plugins/pvalues.py
ibdcluster-1.2.9.dist-info/entry_points.txt
ibdcluster-1.2.9.dist-info/METADATA
ibdcluster-1.2.9.dist-info/WHEEL
ibdcluster-1.2.9.dist-info/RECORD
