Metadata-Version: 2.1
Name: ibdcluster
Version: 1.2.9
Summary: A CLI tool to help identify ibd sharing within networks across a locus of interest at biobank scale and then test for phenotypic enrichment within these networks.
Home-page: https://jtb324.github.io/IBDCluster/
Keywords: python,clustering,IBD,genetics,relatedness
Author: jtb324
Author-email: james.baker@vanderbilt.edu
Maintainer: jtb324
Maintainer-email: james.baker@vanderbilt.edu
Requires-Python: >=3.11,<4.0.0
Classifier: Development Status :: 5 - Production/Stable
Classifier: Intended Audience :: Science/Research
Classifier: Operating System :: POSIX :: Linux
Classifier: Programming Language :: Python :: 3
Classifier: Programming Language :: Python :: 3.11
Classifier: Programming Language :: Python :: 3.11
Classifier: Topic :: Scientific/Engineering :: Bio-Informatics
Requires-Dist: igraph (>=0.10.4,<0.11.0)
Requires-Dist: numpy (>=1.22.2,<2.0.0)
Requires-Dist: pandas (>=1.4.0,<2.0.0)
Requires-Dist: python-dotenv (>=0.19.2,<0.20.0)
Requires-Dist: scipy (>=1.8.0,<2.0.0)
Requires-Dist: toml (>=0.10.2,<0.11.0)
Requires-Dist: tqdm (>=4.62.3,<5.0.0)
Requires-Dist: typer[all] (>=0.7.0,<0.8.0)
Project-URL: Repository, https://github.com/jtb324/IBDCluster
